molde/__init__.py
molde/__main__.py
molde/actors/__init__.py
molde/actors/common_symbols_actor.py
molde/actors/ghost_actor.py
molde/actors/lines_actor.py
molde/actors/round_points_actor.py
molde/actors/square_points_actor.py
molde/colors/__init__.py
molde/colors/color.py
molde/colors/color_names.py
molde/fonts/IBMPlexMono-Bold.ttf
molde/fonts/IBMPlexMono-Regular.ttf
molde/icons/arrow_down_dark_theme.svg
molde/icons/arrow_down_disabled_dark_theme.svg
molde/icons/arrow_down_disabled_light_theme.svg
molde/icons/arrow_down_light_theme.svg
molde/icons/arrow_left_dark_theme.svg
molde/icons/arrow_left_light_theme.svg
molde/icons/arrow_right_dark_theme.svg
molde/icons/arrow_right_light_theme.svg
molde/icons/arrow_up_dark_theme.svg
molde/icons/arrow_up_disabled_dark_theme.svg
molde/icons/arrow_up_disabled_light_theme.svg
molde/icons/arrow_up_light_theme.svg
molde/icons/check_box_image.svg
molde/interactor_styles/__init__.py
molde/interactor_styles/arcball_camera_style.py
molde/interactor_styles/box_selection_style.py
molde/main_window.ui
molde/pickers/__init__.py
molde/pickers/cell_area_picker.py
molde/pickers/cell_property_area_picker.py
molde/poly_data/__init__.py
molde/poly_data/arrows.py
molde/poly_data/lines_data.py
molde/poly_data/simple_shapes.py
molde/poly_data/vertices_data.py
molde/render_widgets/__init__.py
molde/render_widgets/animated_render_widget.py
molde/render_widgets/common_render_widget.py
molde/stylesheets/__init__.py
molde/stylesheets/common.qss
molde/stylesheets/create_color_page.py
molde/stylesheets/mainwindow.ui
molde/stylesheets/qcheckbox.qss
molde/stylesheets/qinputs.qss
molde/stylesheets/qlayouts.qss
molde/stylesheets/qmenubar.qss
molde/stylesheets/qprogressbar.qss
molde/stylesheets/qpushbutton.qss
molde/stylesheets/qradiobutton.qss
molde/stylesheets/qscrollbar.qss
molde/stylesheets/qslider.qss
molde/stylesheets/qtablewidget.qss
molde/stylesheets/qtabwidget.qss
molde/stylesheets/qtoolbar.qss
molde/stylesheets/qtoolbuttons.qss
molde-0.1.19.dist-info/METADATA
molde-0.1.19.dist-info/WHEEL
molde-0.1.19.dist-info/RECORD
