Metadata-Version: 2.4
Name: molde
Version: 0.1.19
Summary: 
Author: André Fernandes
Author-email: fpf.andre@gmail.com
Requires-Python: >=3.10
Classifier: Programming Language :: Python :: 3
Classifier: Programming Language :: Python :: 3.10
Classifier: Programming Language :: Python :: 3.11
Classifier: Programming Language :: Python :: 3.12
Classifier: Programming Language :: Python :: 3.13
Classifier: Programming Language :: Python :: 3.14
Requires-Dist: moviepy (>=1.0.3,<2.0.0)
Requires-Dist: numpy (>=2.0,<3.0)
Requires-Dist: qtpy (>=2.4.2,<3.0.0)
Requires-Dist: vtk (>=9.3.1,<10.0.0)
